{
  "color": {
    "palette": {
      "lime": {
        "5": {
          "value": "#F7FFEA"
        },
        "10": {
          "value": "#EEFED6"
        },
        "20": {
          "value": "#DEFFAB"
        },
        "30": {
          "value": "#CEFE83"
        },
        "40": {
          "value": "#BCF95D"
        },
        "50": {
          "value": "#A1F524"
        },
        "60": {
          "value": "#8EDD13"
        },
        "70": {
          "value": "#699B1C"
        },
        "80": {
          "value": "#476912"
        },
        "90": {
          "value": "#253709"
        }
      }
    }
  }
}
